{
  "conversion_metadata": {
    "converted_at": "2026-02-12T09:41:26.796Z",
    "source_file": "detail95.html"
  },
  "title": "8வது போதும்! தமிழ்நாடு சமூக நலத்துறையில் வேலை – தேர்வு கிடையாது || ரூ.10,000 சம்பளம்! Coimbatore Social Welfare Recruitment 2025",
  "description": "Coimbatore Social Welfare Recruitment 2025: தமிழ்நாடு அரசின் சமூக நலன் மற்றும் பெண்கள் முன்னேற்றம் துறையின் கீழ் செயல்படும் பெண்களுக்கான உதவி எண் அழைப்பு 181 (Women Help Line) செயல்படுத்தப்பட்டு வருகிறது. இதில் பணிபுரிய தகுதியானவர்களிடம் இருந்து விண்ணப்பங்கள் வரவேற்கப்படுகிறது. காலியாக உள்ள பல்வேறு Multi Purpose Helper, Case Worker பணியிடங்களை நிரப்புவதற்கான அறிவிப்பு வெளியிடப்பட்டுள்ளது. எனவே ஆர்வமுள்ள விண்ணப்பதாரர்கள் 30.06.2025 தேதிக்குள் விண்ணப்பிக்குமாறு கேட்டுக் கொள்ளப்படுகிறார்கள். இந்த பணியிடங்களுக்கு யாரெல்லாம் விண்ணப்பிக்கலாம் கல்வி தகுதி என்ன?, விண்ணப்பிப்பது எப்படி? வயது வரம்பு எவ்வளவு? என்பது உள்ளிட்ட விவரங்களை பார்க்கலாம்.",
  "job_details_table": {
    "description": {
      "label": "Description",
      "value": "Details",
      "link": null,
      "link_text": null
    },
    "field_5gnx5": {
      "label": "வேலை பிரிவு",
      "value": "TN Govt Jobs 2025தமிழ்நாடு அரசு வேலை 2025",
      "link": "https://todaytamiljob.com/category/tn-govt-jobs/",
      "link_text": "TN Govt Jobs\n                                        2025"
    },
    "field_1nyjh": {
      "label": "துறைகள்",
      "value": "தமிழக அரசு பெண்கள் உதவி எண் 181",
      "link": null,
      "link_text": null
    },
    "field_dae05": {
      "label": "காலியிடங்கள்",
      "value": "பல்வேறு",
      "link": null,
      "link_text": null
    },
    "field_sdvkf": {
      "label": "பணிகள்",
      "value": "Multi Purpose Helper, Case Worker",
      "link": null,
      "link_text": null
    },
    "field_7j9tu": {
      "label": "விண்ணப்பிக்கும் முறை",
      "value": "தபால் மூலம்",
      "link": null,
      "link_text": null
    },
    "field_9rvho": {
      "label": "கடைசி தேதி",
      "value": "30.06.2025",
      "link": null,
      "link_text": null
    },
    "field_srtm8": {
      "label": "பணியிடம்",
      "value": "தமிழ்நாடு – கோயம்புத்தூர்",
      "link": null,
      "link_text": null
    },
    "field_dxzqr": {
      "label": "அதிகாரப்பூர்வஇணையதளம்",
      "value": "coimbatore.nic.in",
      "link": null,
      "link_text": null
    }
  },
  "positions_table": [],
  "qualifications_table": [
    {
      "position": "பதவி",
      "qualification": "கல்வித் தகுதி"
    },
    {
      "position": "பணி ஒருங்கிணைப்பாளர் (Case Worker)",
      "qualification": "முதுகலை சமூகப் பணி (MSW), M.A./M.Sc. சமூகவியல், M.A./M.Sc. உளவியல் / மருத்துவ உளவியல். (பெண்களுக்கு முன்னுரிமை வழங்கப்படும். கோயம்புத்தூர் மாவட்டத்தைச் சேர்ந்தவராக இருக்க வேண்டும்.)"
    },
    {
      "position": "பல்நோக்கு உதவியாளர் (Multi Purpose Helper)",
      "qualification": "8 ஆம் வகுப்பு தேர்ச்சி அல்லது 10 ஆம் வகுப்பு தேர்ச்சி அல்லது 10 ஆம் வகுப்பு தேர்ச்சி பெறாதவர்கள். (24 மணி நேர சேவை வழங்குவதற்காக பணி சுழற்சி அடிப்படையில் இருக்கும். விருப்பமுள்ளவர்கள் விண்ணப்பிக்கலாம். பெண்களுக்கு முன்னுரிமை வழங்கப்படும். கோயம்புத்தூர் மாவட்டத்தைச் சேர்ந்தவராக இருக்க வேண்டும்.)"
    }
  ],
  "salary_table": [
    {
      "position": "பதவி",
      "salary": "மாதச் சம்பளம்",
      "salary_numeric": [],
      "salary_currency": "Not specified"
    },
    {
      "position": "பணி ஒருங்கிணைப்பாளர் (Case Worker)",
      "salary": "ரூ. 18,000/-",
      "salary_numeric": [
        18000
      ],
      "salary_currency": "Not specified"
    },
    {
      "position": "பல்நோக்கு உதவியாளர் (Multi Purpose\n                                Helper)",
      "salary": "ரூ. 10,000/-",
      "salary_numeric": [
        10000
      ],
      "salary_currency": "Not specified"
    }
  ],
  "application_links_table": {
    "official_notification": null,
    "application_form": null,
    "official_website": {
      "label": "அதிகாரப்பூர்வஇணையதளம்",
      "url": null,
      "text": "coimbatore.nic.in"
    }
  },
  "age_limit": null,
  "selection_process": null,
  "application_fee": null,
  "important_dates": {
    "start_date": null,
    "last_date": null,
    "other_dates": []
  },
  "how_to_apply": null,
  "social_media_links": [
    {
      "platform": "WhatsApp",
      "title": "WhatsApp\n                        Channel",
      "url": "https://whatsapp.com/channel/0029Va4ZViAKAwEffGhQKZ15",
      "is_nofollow": true,
      "is_external": true
    },
    {
      "platform": "Telegram",
      "title": "Telegram\n                        Channel",
      "url": "https://t.me/tamil_job_news",
      "is_nofollow": true,
      "is_external": true
    },
    {
      "platform": "unknown",
      "title": "இன்றைய\n                        வேலைவாய்ப்பு செய்திகள்",
      "url": "https://todaytamiljob.com/",
      "is_nofollow": false,
      "is_external": false
    },
    {
      "platform": "WhatsApp",
      "title": "WhatsApp\n                        Channel",
      "url": "https://whatsapp.com/channel/0029Va4ZViAKAwEffGhQKZ15",
      "is_nofollow": true,
      "is_external": true
    },
    {
      "platform": "Telegram",
      "title": "Telegram\n                        Channel",
      "url": "https://t.me/tamil_job_news",
      "is_nofollow": true,
      "is_external": true
    },
    {
      "platform": "Instagram",
      "title": "Instagram\n                        Channel",
      "url": "https://www.instagram.com/j/AbZ7GMxmLcv2_Gac/",
      "is_nofollow": true,
      "is_external": true
    }
  ],
  "related_jobs": [
    {
      "title": "8வது பாஸ்…தமிழ்நாடு அரசு மதிப்பீடு மற்றும் செயல்முறை ஆராய்ச்சி துறையில் அலுவலக உதவியாளர் வேலை – சம்பளம்: ரூ.15,700 முதல் ரூ.58,100 வரை! TN Evaluation and Applied Research Department Recruitment 2026",
      "url": "https://todaytamiljob.com/tn-evaluation-and-applied-research-department-recruitment-2026/",
      "image": "data:image/svg+xml,%3Csvg%20xmlns='http://www.w3.org/2000/svg'%20viewBox='0%200%20150%20100'%3E%3C/svg%3E"
    },
    {
      "title": "12வது தேர்ச்சி போதும்…தமிழ்நாடு அரசு மருத்துவக்கல்லூரி மருத்துவமனையில் டேட்டா என்ட்ரி ஆபரேட்டர் வேலை – மாதம் ரூ.17,000 சம்பளம் || தேர்வு கிடையாது! Thanjavur Medical College Hospital Recruitment 2026",
      "url": "https://todaytamiljob.com/thanjavur-medical-college-hospital-recruitment-2026/",
      "image": "data:image/svg+xml,%3Csvg%20xmlns='http://www.w3.org/2000/svg'%20viewBox='0%200%20150%20100'%3E%3C/svg%3E"
    },
    {
      "title": "தமிழ்நாடு முழுவதும் மாவட்ட வாரியாக தமிழ்நாடு ஊராக வாழ்வாதார இயக்கத்தில் வேலை -டிகிரி தேர்ச்சி போதும் || சம்பளம்: ரூ.15,000/- TNSLRM Recruitment 2026",
      "url": "https://todaytamiljob.com/tnslrm-recruitment-2026/",
      "image": "data:image/svg+xml,%3Csvg%20xmlns='http://www.w3.org/2000/svg'%20viewBox='0%200%20150%20100'%3E%3C/svg%3E"
    },
    {
      "title": "10th,12th,ITI முடித்தவர்களுக்கு இந்திய இராணுவத்தில்வேலை – ரூ.19,900 முதல் ரூ.63,200 வரை சம்பளம்! Indian Army EME Recruitment 2026",
      "url": "https://todaytamiljob.com/indian-army-eme-recruitment-2026/",
      "image": "data:image/svg+xml,%3Csvg%20xmlns='http://www.w3.org/2000/svg'%20viewBox='0%200%20150%20100'%3E%3C/svg%3E"
    },
    {
      "title": "தமிழ்நாடு வழக்காடல் துறையில் வேலை – 8வது தேர்ச்சி போதும் || சம்பளம்: ரூ.19,500/- முதல் ரூ.71,900/- TN Litigation Department Recruitment 2026",
      "url": "https://todaytamiljob.com/tn-litigation-department-recruitment-2026/",
      "image": "data:image/svg+xml,%3Csvg%20xmlns='http://www.w3.org/2000/svg'%20viewBox='0%200%20150%20100'%3E%3C/svg%3E"
    }
  ],
  "metadata": {
    "author": "Guna",
    "published_date": "June 9, 2025",
    "post_id": "5781",
    "categories": [
      "10th-pass-govt-jobs",
      "8th-pass-govt-jobs",
      "coimbatore-govt-jobs",
      "post-graduate-jobs",
      "tn-govt-jobs"
    ],
    "tags": [
      "coimbatore-social-welfare-recruitment-2025"
    ],
    "published_datetime": null
  }
}