{
  "conversion_metadata": {
    "converted_at": "2026-02-12T09:20:17.675Z",
    "source_file": "F:\\todayjobs\\12th Pass Govt Jobs\\grid_details\\grid61.html",
    "converter_version": "2.0.1"
  },
  "title": "12வது போதும்! குழந்தைகள் பாதுகாப்பு அலகில் டேட்டா எண்ட்ரி ஆபரேட்டர் வேலை – மாதம் ரூ.13,240 சம்பளம் || தேர்வு கிடையாது! DCPU Vellore Recruitment 2025",
  "description": "DCPU Vellore Recruitment 2025: தமிழ்நாடு அரசு சமூக நலன் மற்றும் மகளிர் உரிமை துறையின் கீழ் வேலூர் மாவட்ட குழந்தைகள் பாதுகாப்பு அலுவலகத்தில் காலியாகவுள்ள Assistant cum Data Entry Operator பணியிடங்களை நிரப்புவதற்கான அறிவிப்பு வெளியிடப்பட்டுள்ளது. எனவே ஆர்வமுள்ள விண்ணப்பதாரர்கள் 21.07.2025 தேதிக்குள் விண்ணப்பிக்குமாறு கேட்டுக் கொள்ளப்படுகிறார்கள். இந்த பணியிடங்களுக்கு யாரெல்லாம் விண்ணப்பிக்கலாம் கல்வி தகுதி என்ன?, விண்ணப்பிப்பது எப்படி? வயது வரம்பு எவ்வளவு? என்பது உள்ளிட்ட விவரங்களை பார்க்கலாம்.",
  "job_details_table": {
    "description": {
      "label": "Description",
      "value": "Details",
      "link": null,
      "link_text": null
    },
    "field_sm69i": {
      "label": "வேலை பிரிவு",
      "value": "TN Govt Jobs 2025தமிழ்நாடு அரசு வேலை 2025",
      "link": "https://todaytamiljob.com/category/tn-govt-jobs/",
      "link_text": "TN Govt Jobs 2025"
    },
    "field_hzbd9": {
      "label": "துறைகள்",
      "value": "குழந்தைகள் நலன் மற்றும் சிறப்பு சேவைகள் துறை (DCWSS)வேலூர் மாவட்ட மாவட்ட குழந்தைகள் பாதுகாப்பு அலகு",
      "link": null,
      "link_text": null
    },
    "field_3j51z": {
      "label": "வேலை பெயர்",
      "value": "Assistant cum Data Entry Operator",
      "link": null,
      "link_text": null
    },
    "field_o2088": {
      "label": "விண்ணப்பிக்கும் முறை",
      "value": "தபால் மூலம்",
      "link": null,
      "link_text": null
    },
    "field_674k9": {
      "label": "கடைசி தேதி",
      "value": "21.07.2025",
      "link": null,
      "link_text": null
    },
    "field_qq041": {
      "label": "பணியிடம்",
      "value": "வேலூர், தமிழ்நாடு",
      "link": null,
      "link_text": null
    },
    "field_mudmb": {
      "label": "அதிகாரப்பூர்வஇணையதளம்",
      "value": "https://madurai.nic.in/",
      "link": null,
      "link_text": null
    }
  },
  "positions_table": [],
  "qualifications_table": [],
  "salary_table": [],
  "application_links_table": {
    "official_notification": null,
    "application_form": null,
    "official_website": {
      "label": "அதிகாரப்பூர்வஇணையதளம்",
      "url": null,
      "text": "https://madurai.nic.in/"
    }
  },
  "age_limit": {
    "full_text": "பதவி\n                            \n                        \n                        \n                            Assistant cum Data Entry Operator\n                            விண்ணப்பதாரர்கள் 42 வயதுக்கு\n                                மிகாமல் இருக்க வேண்டும்.",
    "min_age": "42",
    "max_age": null,
    "condition": null
  },
  "selection_process": {
    "description": "தமிழ்நாடு அரசு வேலூர் மாவட்ட மாவட்ட குழந்தைகள் பாதுகாப்பு அலகு வேலைவாய்ப்பு 2025 பணிக்கு தகுதியின் அடிப்படையில் விண்ணப்பதாரர்கள் தனிப்பட்ட நேர்காணல் மற்றும் ஆவண சரிபார்ப்பு ஆகியவற்றைப் பொறுத்து தேர்வு செய்யப்படுவார்கள்.மேலும் விவரங்களுக்கு அதிகாரபூர்வ அறிவிப்பை பார்க்கவும்.",
    "based_on": "Interview"
  },
  "application_fee": {
    "description": "அனைத்து விண்ணப்பதாரர்களுக்கு விண்ணப்பிக்க கட்டணம் கிடையாது. தபால் மூலம் இலவசமாக விண்ணப்பிக்கலாம் \n                .group-card {\n                    margin-bottom: 20px;\n                    position: relative;\n                    border: 2px solid transparent;\n                    border-radius: 5px;\n                    background: #f0f8ff;\n                    display: flex;\n                    align-items: center;\n                    padding: 7px;\n                    justify-content: space-between;\n                    overflow: hidden;\n                }\n\n                .job-card {\n                    animation: job-border-animation 1s infinite;\n                }\n\n                @keyframes job-border-animation {\n                    0% {\n                        border-color: transparent;\n                    }\n\n                    50% {\n                        border-color: #039600;\n                    }\n\n                    100% {\n                        border-color: transparent;\n                    }\n                }\n\n                .seoquake-nofollow {\n                    display: inline-flex;\n                    align-items: center;\n                    justify-content: center;\n                    font-size: 1rem;\n                    font-weight: bold;\n                    text-decoration: none;\n                    padding: 5px 20px;\n                    border-radius: 2px;\n                    flex-shrink: 0;\n                    transition: all 0.3s ease-in-out;\n                    color: white !important;\n                }\n\n                .seoquake-nofollow i {\n                    margin-right: 5px;\n                }\n\n                .job-card .seoquake-nofollow {\n                    background: #039600;\n                }\n\n                .seoquake-nofollow:hover {\n                    transform: scale(1.05);\n                }",
    "is_free": true,
    "amount": 0,
    "currency": "INR"
  },
  "important_dates": {
    "start_date": null,
    "last_date": null,
    "other_dates": []
  },
  "how_to_apply": {
    "instructions": "",
    "postal_address": null,
    "website_url": null,
    "application_mode": "Not specified"
  },
  "social_media_links": [
    {
      "platform": "WhatsApp",
      "title": "WhatsApp\n                        Channel",
      "url": "https://whatsapp.com/channel/0029Va4ZViAKAwEffGhQKZ15",
      "is_nofollow": true,
      "is_external": true
    },
    {
      "platform": "Telegram",
      "title": "Telegram\n                        Channel",
      "url": "https://t.me/tamil_job_news",
      "is_nofollow": true,
      "is_external": true
    },
    {
      "platform": "unknown",
      "title": "இன்றைய\n                        வேலைவாய்ப்பு செய்திகள்",
      "url": "https://todaytamiljob.com/",
      "is_nofollow": false,
      "is_external": false
    },
    {
      "platform": "WhatsApp",
      "title": "WhatsApp\n                        Channel",
      "url": "https://whatsapp.com/channel/0029Va4ZViAKAwEffGhQKZ15",
      "is_nofollow": true,
      "is_external": true
    },
    {
      "platform": "Telegram",
      "title": "Telegram\n                        Channel",
      "url": "https://t.me/tamil_job_news",
      "is_nofollow": true,
      "is_external": true
    },
    {
      "platform": "Instagram",
      "title": "Instagram\n                        Channel",
      "url": "https://www.instagram.com/j/AbZ7GMxmLcv2_Gac/",
      "is_nofollow": true,
      "is_external": true
    }
  ],
  "related_jobs": [
    {
      "title": "12வது தேர்ச்சி போதும்…தமிழ்நாடு அரசு மருத்துவக்கல்லூரி மருத்துவமனையில் டேட்டா என்ட்ரி ஆபரேட்டர் வேலை – மாதம் ரூ.17,000 சம்பளம் || தேர்வு கிடையாது! Thanjavur Medical College Hospital Recruitment 2026",
      "url": "https://todaytamiljob.com/thanjavur-medical-college-hospital-recruitment-2026/",
      "image": "data:image/svg+xml,%3Csvg%20xmlns='http://www.w3.org/2000/svg'%20viewBox='0%200%20150%20100'%3E%3C/svg%3E"
    },
    {
      "title": "தமிழ்நாடு முழுவதும் மாவட்ட வாரியாக தமிழ்நாடு ஊராக வாழ்வாதார இயக்கத்தில் வேலை -டிகிரி தேர்ச்சி போதும் || சம்பளம்: ரூ.15,000/- TNSLRM Recruitment 2026",
      "url": "https://todaytamiljob.com/tnslrm-recruitment-2026/",
      "image": "data:image/svg+xml,%3Csvg%20xmlns='http://www.w3.org/2000/svg'%20viewBox='0%200%20150%20100'%3E%3C/svg%3E"
    },
    {
      "title": "10th,12th,ITI முடித்தவர்களுக்கு இந்திய இராணுவத்தில்வேலை – ரூ.19,900 முதல் ரூ.63,200 வரை சம்பளம்! Indian Army EME Recruitment 2026",
      "url": "https://todaytamiljob.com/indian-army-eme-recruitment-2026/",
      "image": "data:image/svg+xml,%3Csvg%20xmlns='http://www.w3.org/2000/svg'%20viewBox='0%200%20150%20100'%3E%3C/svg%3E"
    },
    {
      "title": "தமிழ்நாடு வழக்காடல் துறையில் வேலை – 8வது தேர்ச்சி போதும் || சம்பளம்: ரூ.19,500/- முதல் ரூ.71,900/- TN Litigation Department Recruitment 2026",
      "url": "https://todaytamiljob.com/tn-litigation-department-recruitment-2026/",
      "image": "data:image/svg+xml,%3Csvg%20xmlns='http://www.w3.org/2000/svg'%20viewBox='0%200%20150%20100'%3E%3C/svg%3E"
    },
    {
      "title": "8வது தேர்ச்சி…தமிழ்நாடு அரசு மாவட்ட வாரியாக ஊராக வளர்ச்சி மற்றும் ஊராட்சி துறையில் வேலை அறிவிப்பு – ரூ.15700 சம்பளம்! TNRD District Wise Recruitment 2026",
      "url": "https://todaytamiljob.com/tnrd-district-wise-recruitment-2026/",
      "image": "data:image/svg+xml,%3Csvg%20xmlns='http://www.w3.org/2000/svg'%20viewBox='0%200%20150%20100'%3E%3C/svg%3E"
    }
  ],
  "metadata": {
    "author": "Guna",
    "published_date": "July 11, 2025",
    "post_id": "6428",
    "categories": [
      "12th-pass-govt-jobs",
      "tn-govt-jobs",
      "vellore-govt-jobs"
    ],
    "tags": [
      "dcpu-vellore-recruitment-2025",
      "tn-dcpu-recruitment-2025",
      "vellore-dcpu-recruitment-2025"
    ],
    "published_datetime": null
  }
}