{
  "conversion_metadata": {
    "converted_at": "2026-02-12T09:41:19.253Z",
    "source_file": "detail58.html"
  },
  "title": "தமிழ்நாடு தெற்கு ரயில்வே துறையில் 3518 அப்ரண்டிஸ் வேலை – 10th, 12th, ITI தேர்ச்சி || தேர்வு கிடையாது! Southern Railway Recruitment 2025",
  "description": "Southern Railway Recruitment 2025: ரயில்வே ஆட்சேர்ப்பு செல் (RRC) தற்போது தெற்கு ரயில்வே துறையில் காலியாகவுள்ள 3518 அப்ரண்ட்டிஸ் பணியிடங்களை நிரப்ப அறிவிப்பு வெளியிட்டுள்ளது. பணியிடம் பெரம்பூர், கோயம்புத்தூர், சென்னை, பொன்மலை, மதுரை, பாலக்காடு, சேலம், திருச்சி, திருவனந்தபுரம். ஆர்வமுள்ள விண்ணப்பதாரர்கள் 25.09.2025 தேதிக்குள் விண்ணப்பிக்கலாம்.. இந்த பணியிடங்களுக்கு யாரெல்லாம் விண்ணப்பிக்கலாம் கல்வி தகுதி என்ன?, விண்ணப்பிப்பது எப்படி? வயது வரம்பு எவ்வளவு? என்பது உள்ளிட்ட விவரங்களை பார்க்கலாம்.",
  "job_details_table": {
    "description": {
      "label": "Description",
      "value": "Details",
      "link": null,
      "link_text": null
    },
    "field_xqtyf": {
      "label": "வேலை பிரிவு",
      "value": "Central Govt Jobs 2025மத்திய அரசு வேலை 2025",
      "link": "https://todaytamiljob.com/category/central-govt-jobs/",
      "link_text": "Central Govt Jobs 2025"
    },
    "field_pbdo9": {
      "label": "துறைகள்",
      "value": "தெற்கு ரயில்வே துறைSouthern Railway",
      "link": null,
      "link_text": null
    },
    "field_ndt5w": {
      "label": "காலியிடங்கள்",
      "value": "3518",
      "link": null,
      "link_text": null
    },
    "field_gvywd": {
      "label": "பணி",
      "value": "அப்ரண்ட்டிஸ் (Apprentices)",
      "link": null,
      "link_text": null
    },
    "field_inhie": {
      "label": "விண்ணப்பிக்கும் முறை",
      "value": "ஆன்லைன் மூலம்",
      "link": null,
      "link_text": null
    },
    "field_4ey7i": {
      "label": "கடைசி தேதி",
      "value": "25.09.2025",
      "link": null,
      "link_text": null
    },
    "field_rsb31": {
      "label": "பணியிடம்",
      "value": "பெரம்பூர், கோயம்புத்தூர், சென்னை, பொன்மலை, மதுரை, பாலக்காடு, சேலம், திருச்சி, திருவனந்தபுரம்",
      "link": null,
      "link_text": null
    },
    "field_to1ym": {
      "label": "அதிகாரப்பூர்வஇணையதளம்",
      "value": "https://sronline.etrpindia.com/",
      "link": "https://sronline.etrpindia.com/rrc_sr_apprenticev1/recruitmentIndex",
      "link_text": "https://sronline.etrpindia.com/"
    }
  },
  "positions_table": [],
  "qualifications_table": [],
  "salary_table": [],
  "application_links_table": {
    "official_notification": null,
    "application_form": null,
    "official_website": {
      "label": "அதிகாரப்பூர்வஇணையதளம்",
      "url": "https://sronline.etrpindia.com/rrc_sr_apprenticev1/recruitmentIndex",
      "text": "https://sronline.etrpindia.com/"
    }
  },
  "age_limit": null,
  "selection_process": {
    "description": "தெற்கு ரயில்வே துறை வேலைவாய்ப்பு 2025 பணிக்கு தகுதியான விண்ணப்பதாரர்கள் பின்வரும் முறைகளின் அடிப்படையில் தேர்வு செய்யப்படுவார்கள்: தகுதி பட்டியல் (Merit List): விண்ணப்பதாரர்களின் கல்வித் தகுதி மதிப்பெண்கள் அடிப்படையில் தகுதி பட்டியல் தயாரிக்கப்படும். ஆவண சரிபார்ப்பு (Document Verification): தகுதி பட்டியலில் இடம்பெறும் விண்ணப்பதாரர்களின் அசல் ஆவணங்கள் சரிபார்க்கப்படும். குறிப்பு: தேர்வாகும் விண்ணப்பதாரர்கள் வட மாநிலங்களில் பணியமத்த்தப்படுவார்கள்.",
    "based_on": "Merit"
  },
  "application_fee": {
    "description": "SC/ST/Ex-Servicemen/PwBD விண்ணப்பதாரர்களுக்கு – கட்டணம் இல்லை\n\n\n\n                மற்ற விண்ணப்பதாரர்களுக்கு – ரூ.100/-\n\n\n\n                கட்டண முறை: ஆன்லைன்\n             \n                .group-card {\n                    margin-bottom: 20px;\n                    position: relative;\n                    border: 2px solid transparent;\n                    border-radius: 5px;\n                    background: #f0f8ff;\n                    display: flex;\n                    align-items: center;\n                    padding: 7px;\n                    justify-content: space-between;\n                    overflow: hidden;\n                }\n\n                .job-card {\n                    animation: job-border-animation 1s infinite;\n                }\n\n                @keyframes job-border-animation {\n                    0% {\n                        border-color: transparent;\n                    }\n\n                    50% {\n                        border-color: #039600;\n                    }\n\n                    100% {\n                        border-color: transparent;\n                    }\n                }\n\n                .seoquake-nofollow {\n                    display: inline-flex;\n                    align-items: center;\n                    justify-content: center;\n                    font-size: 1rem;\n                    font-weight: bold;\n                    text-decoration: none;\n                    padding: 5px 20px;\n                    border-radius: 2px;\n                    flex-shrink: 0;\n                    transition: all 0.3s ease-in-out;\n                    color: white !important;\n                }\n\n                .seoquake-nofollow i {\n                    margin-right: 5px;\n                }\n\n                .job-card .seoquake-nofollow {\n                    background: #039600;\n                }\n\n                .seoquake-nofollow:hover {\n                    transform: scale(1.05);\n                }",
    "is_free": false,
    "amount": 100,
    "currency": "INR"
  },
  "important_dates": {
    "start_date": null,
    "last_date": null,
    "other_dates": []
  },
  "how_to_apply": {
    "instructions": "",
    "postal_address": null,
    "website_url": null,
    "application_mode": "Not specified"
  },
  "social_media_links": [
    {
      "platform": "unknown",
      "title": "இன்றைய\n                        வேலைவாய்ப்பு செய்திகள்",
      "url": "https://todaytamiljob.com/",
      "is_nofollow": false,
      "is_external": false
    },
    {
      "platform": "WhatsApp",
      "title": "WhatsApp\n                        Channel",
      "url": "https://whatsapp.com/channel/0029Va4ZViAKAwEffGhQKZ15",
      "is_nofollow": true,
      "is_external": true
    },
    {
      "platform": "Telegram",
      "title": "Telegram\n                        Channel",
      "url": "https://t.me/tamil_job_news",
      "is_nofollow": true,
      "is_external": true
    },
    {
      "platform": "Instagram",
      "title": "Instagram\n                        Channel",
      "url": "https://www.instagram.com/j/AbZ7GMxmLcv2_Gac/",
      "is_nofollow": true,
      "is_external": true
    }
  ],
  "related_jobs": [
    {
      "title": "12வது தேர்ச்சி போதும்…தமிழ்நாடு அரசு மருத்துவக்கல்லூரி மருத்துவமனையில் டேட்டா என்ட்ரி ஆபரேட்டர் வேலை – மாதம் ரூ.17,000 சம்பளம் || தேர்வு கிடையாது! Thanjavur Medical College Hospital Recruitment 2026",
      "url": "https://todaytamiljob.com/thanjavur-medical-college-hospital-recruitment-2026/",
      "image": "data:image/svg+xml,%3Csvg%20xmlns='http://www.w3.org/2000/svg'%20viewBox='0%200%20150%20100'%3E%3C/svg%3E"
    },
    {
      "title": "இந்திய கடற்ப்படை வேலைவாய்ப்பு 2026 – 260 காலியிடங்கள் || ரூ. 1,25,000 சம்பளம்! Indian Navy Recruitment 2026",
      "url": "https://todaytamiljob.com/indian-navy-recruitment-2026/",
      "image": "data:image/svg+xml,%3Csvg%20xmlns='http://www.w3.org/2000/svg'%20viewBox='0%200%20150%20100'%3E%3C/svg%3E"
    },
    {
      "title": "10th,12th,ITI முடித்தவர்களுக்கு இந்திய இராணுவத்தில்வேலை – ரூ.19,900 முதல் ரூ.63,200 வரை சம்பளம்! Indian Army EME Recruitment 2026",
      "url": "https://todaytamiljob.com/indian-army-eme-recruitment-2026/",
      "image": "data:image/svg+xml,%3Csvg%20xmlns='http://www.w3.org/2000/svg'%20viewBox='0%200%20150%20100'%3E%3C/svg%3E"
    },
    {
      "title": "டிகிரி போதும்.. அரசு பொதுத்துறை வங்கியில் அப்ரண்டிஸ் வேலை – 5138 காலியிடங்கள் || சம்பளம்: ரூ.15,000/- PNB Apprentice Recruitment 2026",
      "url": "https://todaytamiljob.com/pnb-apprentice-recruitment-2026/",
      "image": "data:image/svg+xml,%3Csvg%20xmlns='http://www.w3.org/2000/svg'%20viewBox='0%200%20150%20100'%3E%3C/svg%3E"
    },
    {
      "title": "8வது தேர்ச்சி…தமிழ்நாடு அரசு மாவட்ட வாரியாக ஊராக வளர்ச்சி மற்றும் ஊராட்சி துறையில் வேலை அறிவிப்பு – ரூ.15700 சம்பளம்! TNRD District Wise Recruitment 2026",
      "url": "https://todaytamiljob.com/tnrd-district-wise-recruitment-2026/",
      "image": "data:image/svg+xml,%3Csvg%20xmlns='http://www.w3.org/2000/svg'%20viewBox='0%200%20150%20100'%3E%3C/svg%3E"
    }
  ],
  "metadata": {
    "author": "Guna",
    "published_date": "August 26, 2025",
    "post_id": "6913",
    "categories": [
      "10th-pass-govt-jobs",
      "12th-pass-govt-jobs",
      "central-govt-jobs",
      "chennai-govt-jobs",
      "coimbatore-govt-jobs",
      "iti-govt-jobs",
      "madurai-govt-jobs",
      "perambalur-govt-jobs",
      "railway-jobs",
      "trichy-govt-jobs"
    ],
    "tags": [
      "railway-recruitment-2025",
      "rrc-southern-railway-recruitment-2025",
      "southern-railway-recruitment-2025"
    ],
    "published_datetime": null
  }
}